{
  "full_name": "Mokesh Nagpal",
  "professional_summary": "An aspiring Data Scientist with strong technical skills in web technologies, programming, and data visualization. A fluent coder, curious learner, and innovative problem-solver dedicated to driving actionable insights.",
  "work_experience": [
    {
      "position": "Placement Coordinator",
      "company": "Training and Placemnt Cell, BIT - Mesra",
      "description": "Led innovative initiatives and managed team operations to enhance hostel activities.",
      "start_date": "2025",
      "end_date": "2026"
    },
    {
      "position": "Vice President",
      "company": "Hostel 4 Committee, LPU",
      "description": "Led innovative initiatives and managed team operations to enhance hostel activities.",
      "start_date": "2023",
      "end_date": "2023"
    },
    {
      "position": "Class Representative",
      "company": "School of Computer Applications, LPU",
      "description": "Coordinated academic and extracurricular events to represent and support the class.",
      "start_date": "2022",
      "end_date": "2024"
    }
  ],
  "education": [
    {
      "degree": "Master of Computer Applications",
      "institution": "Birla Institute of Technoloogy, Mesra",
      "start_date": "Aug '24",
      "end_date": "July '26 (Expected)",
      "details": "C.G.P.A. - 8.97"
    },
    {
      "degree": "Bachelor of Computer Applications",
      "institution": "Lovely Professional University, Pharwara",
      "start_date": "Aug '21",
      "end_date": "July '24",
      "details": "C.G.P.A. - 9.43"
    }
  ],
  "skills": {
    "programming_languages": ["Python", "R", "C", "C++", "Micropython"],
    "web_technologies": ["Flask", "HTML5", "CSS", "JavaScript", "PHP"],
    "databases": ["MySQL", "Firebase"],
    "data_visualization": ["Tableau"],
    "machine_learning": ["Machine Learning", "Deep Learning", "Data Science"],
    "embedded_systems": ["Arduino", "MicroPython", "Tkinter"],
    "algorithms": ["Data Structures and Algorithms"]
  },
  "projects": [
    {
      "image_url": "Hard Coded MLP.jpg",
      "title": "Hard Coded MLP",
      "description": "Implemented a hard-coded multi-layer perceptron to demonstrate neural network fundamentals.",
      "date": "Apr '25",
      "technologies": ["Python"],
      "project_type": "Machine Learning",
      "project_category": "Mini",
      "stream": "Data Science & AI",
      "show": "Yes"
    },
    {
      "image_url": "Indus Valley Script Analysis.jpg",
      "title": "Indus Valley Script Analysis",
      "description": "Applied deep-learning segmentation to extract and classify symbols on 100 Indus Valley seals; performed statistical and pattern analysis to assist epigraphic research.",
      "date": "Mar '25",
      "technologies": ["Python", "U‑Net (Keras)", "OpenCV"],
      "project_type": "Image Segmentation / Historical Linguistics",
      "project_category": "Major",
      "stream": "Data Science & AI",
      "show": "Yes"
    },
    {
      "image_url": "Security Management Website.jpg",
      "title": "Security Management Website",
      "description": "Built a web-based security management system using the Flask framework to manage access and monitor security protocols.",
      "date": "Feb '25",
      "technologies": ["Flask", "HTML", "CSS", "JavaScript"],
      "project_type": "Web Development",
      "project_category": "Mini",
      "stream": "Web Development",
      "show": "Yes"
    },
    {
      "image_url": "Adaptive Traffic Management System.jpg",
      "title": "Adaptive Traffic Management System",
      "description": "Developed a deep learning solution to reduce traffic congestion with image processing.",
      "date": "Sep '24",
      "technologies": ["Python", "Flask"],
      "project_type": "Deep Learning / AI",
      "project_category": "Major",
      "stream": "Data Science & AI",
      "show": "Yes"
    },
    {
      "image_url": "OTP Verification App.jpg",
      "title": "OTP Verification App",
      "description": "Implemented an OTP verification system to enhance security in user authentication processes.",
      "date": "Sep '24",
      "technologies": ["Python"],
      "project_type": "Security Application",
      "project_category": "Mini",
      "stream": "Web Development",
      "show": "No"
    },
    {
      "image_url": "BMI Calculator App.jpg",
      "title": "BMI Calculator App",
      "description": "Developed an app that calculates the Body Mass Index (BMI) based on user input, with a graphical interface.",
      "date": "Sep '24",
      "technologies": ["Python", "Tkinter"],
      "project_type": "GUI Application Development",
      "project_category": "Mini",
      "stream": "Application & Game Development",
      "show": "No"
    },
    {
      "image_url": "Rock Paper Scissors App.jpg",
      "title": "Rock Paper Scissors App",
      "description": "Built a Rock Paper Scissors game application featuring an interactive GUI.",
      "date": "Sep '24",
      "technologies": ["Python", "Tkinter"],
      "project_type": "Game Development",
      "project_category": "Mini",
      "stream": "Application & Game Development",
      "show": "No"
    },
    {
      "image_url": "Library Management App.jpg",
      "title": "Library Management App",
      "description": "Developed a library management system to streamline book inventory, borrowing, and returns.",
      "date": "Sep '24",
      "technologies": ["Python", "Tkinter"],
      "project_type": "Information Management",
      "project_category": "Major",
      "stream": "Application & Game Development",
      "show": "No"
    },
    {
      "image_url": "Hangman App.jpg",
      "title": "Hangman App",
      "description": "Created a Hangman game using Tkinter to provide a fun and interactive word guessing experience.",
      "date": "Sep '24",
      "technologies": ["Python", "Tkinter"],
      "project_type": "Game Development",
      "project_category": "Mini",
      "stream": "Application & Game Development",
      "show": "No"
    },
    {
      "image_url": "Number Guessing App.jpg",
      "title": "Number Guessing App",
      "description": "Created a number guessing game that challenges users to guess a randomly generated number.",
      "date": "Aug '24",
      "technologies": ["Python", "Tkinter"],
      "project_type": "Game Development",
      "project_category": "Mini",
      "stream": "Application & Game Development",
      "show": "No"
    },
    {
      "image_url": "Python Calculator.jpg",
      "title": "Python Calculator",
      "description": "Implemented a calculator application in Python for performing basic arithmetic operations.",
      "date": "Aug '24",
      "technologies": ["Python", "Tkinter"],
      "project_type": "GUI Application Development",
      "project_category": "Mini",
      "stream": "Application & Game Development",
      "show": "No"
    },
    {
      "image_url": "Image Viewer.jpg",
      "title": "Image Viewer",
      "description": "Developed an image viewer application that allows users to browse and display images.",
      "date": "Aug '24",
      "technologies": ["Python", "Tkinter"],
      "project_type": "GUI Application Development",
      "project_category": "Mini",
      "stream": "Application & Game Development",
      "show": "No"
    },
    {
      "image_url": "Password Encrypter App.jpg",
      "title": "Password Encrypter App",
      "description": "Created an application to encrypt and securely store passwords using standard encryption algorithms.",
      "date": "Aug '24",
      "technologies": ["Python"],
      "project_type": "Security Application",
      "project_category": "Mini",
      "stream": "Application & Game Development",
      "show": "No"
    },
    {
      "image_url": "Weather App.jpg",
      "title": "Weather App",
      "description": "Developed a weather application that fetches and displays real-time weather data.",
      "date": "Aug '24",
      "technologies": ["Python", "Tkinter", "API Integration"],
      "project_type": "Web Application",
      "project_category": "Mini",
      "stream": "Web Development",
      "show": "No"
    },
    {
      "image_url": "QR Code App.jpg",
      "title": "QR Code App",
      "description": "Built an application for generating and scanning QR codes for quick data sharing.",
      "date": "Aug '24",
      "technologies": ["Python", "OpenCV", "Tkinter"],
      "project_type": "Image Processing / Utility",
      "project_category": "Mini",
      "stream": "Application & Game Development",
      "show": "No"
    },
    {
      "image_url": "Moisture Detection and Prediction System.jpg",
      "title": "Moisture Detection and Prediction System",
      "description": "Created a Flask-based server and app for real-time sensor data input and moisture prediction.",
      "date": "Jun '24",
      "technologies": ["Python", "HTML", "CSS", "JavaScript", "MicroPython"],
      "project_type": "Web Application / IoT",
      "project_category": "Major",
      "stream": "IoT & Embedded Systems",
      "show": "Yes"
    },
    {
      "image_url": "Data Analysis on Climate Change.jpg",
      "title": "Data Analysis on Climate Change",
      "description": "Analyzed climate data, handled missing values with regression, and forecasted indicators using ARIMA.",
      "date": "Apr '24",
      "technologies": ["R Studios"],
      "project_type": "Data Analysis / Statistical Methods",
      "project_category": "Major",
      "stream": "Data Science & AI",
      "show": "Yes"
    },
    {
      "image_url": "Bird Species Detection.jpg",
      "title": "Bird Species Detection",
      "description": "Developed an application for bird species detection, combining Tkinter for the GUI and YOLO for real-time object detection.",
      "date": "Apr '24",
      "technologies": ["Python", "Tkinter", "YOLO"],
      "project_type": "Computer Vision / AI",
      "project_category": "Major",
      "stream": "Data Science & AI",
      "show": "No"
    },
    {
      "image_url": "Solar Cell Follower.jpg",
      "title": "Solar Cell Follower",
      "description": "Created a solar cell follower using ESP8266 to ensure optimal alignment of solar panels with the sun’s position.",
      "date": "Nov '23",
      "technologies": ["ESP8266"],
      "project_type": "IoT Application",
      "project_category": "Mini",
      "stream": "IoT & Embedded Systems",
      "show": "No"
    },
    {
      "image_url": "Data Visualization on Death and Wars.jpg",
      "title": "Data Visualization on Death and Wars",
      "description": "Preprocessed data and created interactive visualizations using Tableau and R.",
      "date": "Oct '23",
      "technologies": ["Tableau", "R"],
      "project_type": "Data Visualization",
      "project_category": "Major",
      "stream": "Data Science & AI",
      "show": "No"
    },
    {
      "image_url": "Fingerprint Security System.jpg",
      "title": "Fingerprint Security System",
      "description": "Implemented a fingerprint-based security system using ESP32 for secure access control.",
      "date": "Oct '23",
      "technologies": ["ESP32"],
      "project_type": "IoT Application",
      "project_category": "Mini",
      "stream": "IoT & Embedded Systems",
      "show": "No"
    },
    {
      "image_url": "Electricity Analysis with R.jpg",
      "title": "Electricity Analysis with R",
      "description": "Conducted an analysis of electricity availability using different types of fuels, employing R for statistical computation and data visualization.",
      "date": "Sep '23",
      "technologies": ["R"],
      "project_type": "Data Analysis",
      "project_category": "Mini",
      "stream": "Data Science & AI",
      "show": "No"
    },
    {
      "image_url": "Weather Station.jpg",
      "title": "Weather Station",
      "description": "Built a weather station using ESP32 to collect and display real-time environmental data.",
      "date": "May '23",
      "technologies": ["ESP32"],
      "project_type": "IoT Application",
      "project_category": "Mini",
      "stream": "IoT & Embedded Systems",
      "show": "No"
    },
    {
      "image_url": "Smart Watch.jpg",
      "title": "Smart Watch",
      "description": "Developed a smart watch project using ESP32 to integrate various wearable functionalities.",
      "date": "May '23",
      "technologies": ["ESP32"],
      "project_type": "IoT Application",
      "project_category": "Mini",
      "stream": "IoT & Embedded Systems",
      "show": "No"
    },
    {
      "image_url": "C Tic Tac Toe Game.jpg",
      "title": "C Tic Tac Toe Game",
      "description": "Developed a Tic Tac Toe game in C featuring both single-player (against the computer) and multiplayer modes with a graphical user interface.",
      "date": "Jan '23",
      "technologies": ["C", "GUI Libraries"],
      "project_type": "Game Development",
      "project_category": "Mini",
      "stream": "Application & Game Development",
      "show": "No"
    },
    {
      "image_url": "E-Commerce Website.jpg",
      "title": "E-Commerce Website",
      "description": "Built a revenue-generating website using HTML, CSS, JavaScript, MySQL, and PHP.",
      "date": "Dec '22",
      "technologies": ["HTML", "CSS", "JavaScript", "MySQL", "PHP"],
      "project_type": "Web Development",
      "project_category": "Major",
      "stream": "Web Development",
      "show": "Yes"
    },
    {
      "image_url": "Registration and Login System in C.jpg",
      "title": "Registration and Login System in C",
      "description": "Created a user registration and login page using mouse programming and GUI in C to demonstrate interactive application development.",
      "date": "Dec '22",
      "technologies": ["C", "GUI Libraries"],
      "project_type": "GUI Application Development",
      "project_category": "Mini",
      "stream": "Application & Game Development",
      "show": "No"
    },
    {
      "image_url": "Automated Floor Cleaner.jpg",
      "title": "Automated Floor Cleaner",
      "description": "Developed an automated floor cleaner project using Arduino to control and coordinate cleaning operations.",
      "date": "Nov '22",
      "technologies": ["Arduino"],
      "project_type": "Embedded Systems / Robotics",
      "project_category": "Mini",
      "stream": "IoT & Embedded Systems",
      "show": "No"
    }
  ],
  "patents": [
    {
      "image_url": "Sustainable Elevator.jpg",
      "title": "Sustainable Elevator | Applied",
      "description": "Optimized algorithm for elevator movement with energy regeneration and emergency handling.",
      "date": "Feb '24",
      "domain": "IOT, Mechanical, Electrical, Automation",
      "stream": "IoT & Embedded Systems"
    },
    {
      "image_url": "Smart Pillow.jpg",
      "title": "Smart Pillow | 202311080891",
      "description": "Developed a prototype that adjusts pillow dimensions based on sleeping posture.",
      "date": "Dec '23",
      "technologies": ["Machine Learning", "Image Processinng", "IOT", "Automation"],
      "domain": "IOT, Machine Learning",
      "stream": "IoT & Embedded Systems"
    },
    {
      "image_url": "Smart Container.jpg",
      "title": "Smart Container | 202311020732 A",
      "description": "Developed a prototype that allows the measurement of any flowable material such as spices, sugar, rice, etc. present in a container.",
      "date": "Mar '23",
      "domain": "IOT, Automation",
      "stream": "IoT & Embedded Systems"
    },
    {
      "image_url": "Smart Room.jpg",
      "title": "Smart Room | 202311042366 A",
      "description": "Developed a prototype that uses ultrasonic for human presence and other smart technologies to save electricity in a household.",
      "date": "Mar '23",
      "domain": "IOT, Automation",
      "stream": "IoT & Embedded Systems"
    }
  ],
  "social_links": {
    "github": "https://github.com/mokeshnagpal",
    "linkedin": "https://www.linkedin.com/in/mokeshnagpal",
    "email": "nagpalmokesh@gmail.com",
    "phone": "+91 9903855585"
  }
}
